wscrape/__init__.py
wscrape-0.0.1.dist-info/LICENSE
wscrape-0.0.1.dist-info/METADATA
wscrape-0.0.1.dist-info/WHEEL
wscrape-0.0.1.dist-info/top_level.txt
wscrape-0.0.1.dist-info/RECORD
