Metadata-Version: 2.1
Name: wscrape
Version: 0.0.1
Summary: A small package that allows you to quickly scrape things off the web.
Home-page: https://github.com/GoodMusic8596/wscrape
Author: Crow Randalf
Author-email: somethings8596@gmail.com
License: UNKNOWN
Platform: UNKNOWN
Classifier: Programming Language :: Python :: 3
Classifier: License :: OSI Approved :: MIT License
Classifier: Operating System :: OS Independent
Requires-Python: >=3.8
License-File: LICENSE
